{
    "sol":{
        "images": ["bg_sol.jpg"],
        "variables":{
            "fondApplication": "url(../images/bg_sol.jpg) #000",
            "couleurFondPage": "rgba(255, 255, 255, 0.800)",
            "couleurTextePage": "rgb(36, 36, 36)",
            "couleurFondSidePanel": "linear-gradient(160deg, #ffffff 0%,#dadada 100%)",
            "couleurFondTitre1": "linear-gradient(160deg, #63574d 0%,#2b2b2b 100%)",
            "couleurTexteTitre1": "rgb(255, 255, 255)",
            "couleurTexteTitre2": "rgb(85, 85, 85)",
            "couleurBordureTitre2": "rgb(85, 85, 85)",
            "couleurTexteCitation": "rgb(36, 36, 36)",
            "fondCitation": "rgba(85, 85, 85, 0.329)",
            "couleurBordureEncart": "rgb(85, 85, 85)",
            "couleurFondEncart": "rgba(255, 255, 255, 0.418)",
            "couleurFondTableau": "rgb(85, 85, 85)",
            "couleurTexteTitreTableaux": "rgba(255, 255, 255, 0.9)",
            "couleurFondTitreTableaux": "transparent",
            "couleurFondCelluleTableaux": "rgba(255, 255, 255, 0.85)",
            "couleurTexteCelluleTableaux": "rgb(0, 0, 0)",
            "fondBouton": "linear-gradient(160deg, #b7b194 0%,#666666 100%)",
            "couleurBoutons": "rgb(102, 102, 102)",
            "couleurTexteBoutons": "rgb(255, 255, 255)",
            "couleurBoutonsBad": "linear-gradient(160deg, #d12c2c 0%,#7c1b1b 100%)",
            "couleurTexteBoutonsBad": "rgb(255, 255, 255)",
            "couleurBoutonsClair": "linear-gradient(160deg, #ffffff 0%,#dadada 100%)",
            "couleurTexteBoutonsClair": "#3b3b3b",
            "couleurFondSelecteurs": "rgb(77, 77, 77)",
            "couleurTexteSelecteur": "rgb(0, 0, 0)",
            "couleurFondSelecteursSelection": "rgb(94, 194, 94)",
            "couleurTexteSelecteurSelection": "rgb(0, 0, 0)",
            "couleurFondInfosSelecteur": "rgba(255, 255, 255, 0.418)",
            "couleurTexteInfosSelecteur": "rgba(0, 0, 0, 0.822)",
            "couleurPlaceholderSelecteur": "rgba(0, 0, 0, 0.562)",
            "couleurLabelSelecteurOn": "rgba(0, 0, 0, 0.959)",
            "couleurLabelSelecteurOff": "rgba(0, 0, 0, 0.397)"
        }
    },
    "terre":{
        "images": ["bg_terre.jpg"],
        "variables":{
            "fondApplication": "url(../images/bg_terre.jpg) #000",
            "couleurFondPage": "rgba(255, 255, 255, 0.800)",
            "couleurTextePage": "rgb(36, 36, 36)",
            "couleurFondSidePanel": "linear-gradient(160deg, #ffffff 0%,#dcf1ff 100%)",
            "couleurFondTitre1": "linear-gradient(160deg, #547e99 0%,#003b59 100%)",
            "couleurTexteTitre1": "rgb(255, 255, 255)",
            "couleurTexteTitre2": "rgb(29, 71, 99)",
            "couleurBordureTitre2": "rgb(29, 71, 99)",
            "couleurTexteCitation": "rgb(36, 36, 36)",
            "fondCitation": "rgba(29, 71, 99, 0.329)",
            "couleurBordureEncart": "rgb(29, 71, 99)",
            "couleurFondEncart": "rgba(255, 255, 255, 0.418)",
            "couleurFondTableau": "rgb(29, 71, 99)",
            "couleurTexteTitreTableaux": "rgba(255, 255, 255, 0.9)",
            "couleurFondTitreTableaux": "transparent",
            "couleurFondCelluleTableaux": "rgba(255, 255, 255, 0.85)",
            "couleurTexteCelluleTableaux": "rgb(0, 0, 0)",
            "fondBouton": "linear-gradient(160deg, #30bee5 0%,#2871a1 100%)",
            "couleurBoutons": "rgb(40, 113, 161)",
            "couleurTexteBoutons": "rgb(255, 255, 255)",
            "couleurBoutonsBad": "linear-gradient(160deg, #d12c2c 0%,#7c1b1b 100%)",
            "couleurTexteBoutonsBad": "rgb(255, 255, 255)",
            "couleurBoutonsClair": "linear-gradient(160deg, #ffffff 0%,#dcf1ff 100%)",
            "couleurTexteBoutonsClair": "rgb(17, 55, 80)",
            "couleurFondSelecteurs": "rgb(60, 151, 212)",
            "couleurTexteSelecteur": "rgb(0, 0, 0)",
            "couleurFondSelecteursSelection": "rgb(94, 194, 94)",
            "couleurTexteSelecteurSelection": "rgb(0, 0, 0)",
            "couleurFondInfosSelecteur": "rgba(255, 255, 255, 0.418)",
            "couleurTexteInfosSelecteur": "rgba(0, 0, 0, 0.822)",
            "couleurPlaceholderSelecteur": "rgba(0, 0, 0, 0.562)",
            "couleurLabelSelecteurOn": "rgba(0, 0, 0, 0.959)",
            "couleurLabelSelecteurOff": "rgba(0, 0, 0, 0.397)"
        }
    },
    "mars":{
        "images": ["bg_mars.jpg"],
        "variables":{
            "fondApplication": "url(../images/bg_mars.jpg) #000",
            "couleurFondPage": "rgba(255, 255, 255, 0.800)",
            "couleurTextePage": "rgb(36, 36, 36)",
            "couleurFondSidePanel": "linear-gradient(160deg, #ffffff 0%,rgb(255, 234, 212) 100%)",
            "couleurFondTitre1": "linear-gradient(160deg, #6d553d 0%,#542e1e 100%)",
            "couleurTexteTitre1": "rgb(255, 255, 255)",
            "couleurTexteTitre2": "rgb(99, 71, 29)",
            "couleurBordureTitre2": "rgb(99, 71, 29)",
            "couleurTexteCitation": "rgb(36, 36, 36)",
            "fondCitation": "rgba(99, 71, 29, 0.329)",
            "couleurBordureEncart": "rgb(99, 71, 29)",
            "couleurFondEncart": "rgba(255, 255, 255, 0.418)",
            "couleurFondTableau": "rgb(99, 71, 29)",
            "couleurTexteTitreTableaux": "rgba(255, 255, 255, 0.9)",
            "couleurFondTitreTableaux": "transparent",
            "couleurFondCelluleTableaux": "rgba(255, 255, 255, 0.85)",
            "couleurTexteCelluleTableaux": "rgb(0, 0, 0)",
            "fondBouton": "linear-gradient(160deg, #937352 0%,#724328 100%)",
            "couleurBoutons": "rgb(150, 133, 115)",
            "couleurTexteBoutons": "rgb(255, 255, 255)",
            "couleurBoutonsBad": "linear-gradient(160deg, #d12c2c 0%,#7c1b1b 100%)",
            "couleurTexteBoutonsBad": "rgb(255, 255, 255)",
            "couleurBoutonsClair": "linear-gradient(160deg, #ffffff 0%,rgb(255, 234, 212) 100%)",
            "couleurTexteBoutonsClair": "rgb(58, 50, 41)",
            "couleurFondSelecteurs": "linear-gradient(160deg, #bb9d7c 0%,#594b3b 100%)",
            "couleurTexteSelecteur": "rgb(0, 0, 0)",
            "couleurFondSelecteursSelection": "linear-gradient(160deg, #5ec25e 0%,#2f6032 100%)",
            "couleurTexteSelecteurSelection": "rgb(0, 0, 0)",
            "couleurFondInfosSelecteur": "rgba(255, 255, 255, 0.418)",
            "couleurTexteInfosSelecteur": "rgba(0, 0, 0, 0.822)",
            "couleurPlaceholderSelecteur": "rgba(0, 0, 0, 0.562)",
            "couleurLabelSelecteurOn": "rgba(0, 0, 0, 0.959)",
            "couleurLabelSelecteurOff": "rgba(0, 0, 0, 0.397)"
        }
    },
    "jupiter":{
        "images": ["bg_jupiter.jpg"],
        "variables":{
            "fondApplication": "url(../images/bg_mars.jpg) #000",
            "couleurFondPage": "rgba(255, 255, 255, 0.800)",
            "couleurTextePage": "rgb(36, 36, 36)",
            "couleurFondSidePanel": "linear-gradient(160deg, #ffffff 0%,rgb(255, 234, 212) 100%)",
            "couleurFondTitre1": "linear-gradient(160deg, #25697c 0%,#1d4763 100%)",
            "couleurTexteTitre1": "rgb(255, 255, 255)",
            "couleurTexteTitre2": "rgb(99, 71, 29)",
            "couleurBordureTitre2": "rgb(99, 71, 29)",
            "couleurTexteCitation": "rgb(36, 36, 36)",
            "fondCitation": "rgba(99, 71, 29, 0.329)",
            "couleurBordureEncart": "rgb(99, 71, 29)",
            "couleurFondEncart": "rgba(255, 255, 255, 0.418)",
            "couleurFondTableau": "rgb(99, 71, 29)",
            "couleurTexteTitreTableaux": "rgba(255, 255, 255, 0.9)",
            "couleurFondTitreTableaux": "transparent",
            "couleurFondCelluleTableaux": "rgba(255, 255, 255, 0.85)",
            "couleurTexteCelluleTableaux": "rgb(0, 0, 0)",
            "fondBouton": "linear-gradient(160deg, #30bee5 0%,#2871a1 100%)",
            "couleurBoutons": "rgb(150, 133, 115)",
            "couleurTexteBoutons": "rgb(255, 255, 255)",
            "couleurBoutonsBad": "linear-gradient(160deg, #d12c2c 0%,#7c1b1b 100%)",
            "couleurTexteBoutonsBad": "rgb(255, 255, 255)",
            "couleurBoutonsClair": "linear-gradient(160deg, #ffffff 0%,rgb(255, 234, 212) 100%)",
            "couleurTexteBoutonsClair": "rgb(58, 50, 41)",
            "couleurFondSelecteurs": "rgb(185, 157, 124)",
            "couleurTexteSelecteur": "rgb(0, 0, 0)",
            "couleurFondSelecteursSelection": "rgb(94, 194, 94)",
            "couleurTexteSelecteurSelection": "rgb(0, 0, 0)",
            "couleurFondInfosSelecteur": "rgba(255, 255, 255, 0.418)",
            "couleurTexteInfosSelecteur": "rgba(0, 0, 0, 0.822)",
            "couleurPlaceholderSelecteur": "rgba(0, 0, 0, 0.562)",
            "couleurLabelSelecteurOn": "rgba(0, 0, 0, 0.959)",
            "couleurLabelSelecteurOff": "rgba(0, 0, 0, 0.397)"
        }
    },
    "saturne":{
        "images": ["bg_saturne.jpg"],
        "variables":{
            "fondApplication": "url(../images/bg_sol.jpg) #000",
            "couleurFondPage": "rgba(255, 255, 255, 0.800)",
            "couleurTextePage": "rgb(36, 36, 36)",
            "couleurFondSidePanel": "linear-gradient(160deg, #ffffff 0%,#dadada 100%)",
            "couleurFondTitre1": "linear-gradient(160deg, #63574d 0%,#2b2b2b 100%)",
            "couleurTexteTitre1": "rgb(255, 255, 255)",
            "couleurTexteTitre2": "rgb(85, 85, 85)",
            "couleurBordureTitre2": "rgb(85, 85, 85)",
            "couleurTexteCitation": "rgb(36, 36, 36)",
            "fondCitation": "rgba(85, 85, 85, 0.329)",
            "couleurBordureEncart": "rgb(85, 85, 85)",
            "couleurFondEncart": "rgba(255, 255, 255, 0.418)",
            "couleurFondTableau": "rgb(85, 85, 85)",
            "couleurTexteTitreTableaux": "rgba(255, 255, 255, 0.9)",
            "couleurFondTitreTableaux": "transparent",
            "couleurFondCelluleTableaux": "rgba(255, 255, 255, 0.85)",
            "couleurTexteCelluleTableaux": "rgb(0, 0, 0)",
            "fondBouton": "linear-gradient(160deg, #30bee5 0%,#2871a1 100%)",
            "couleurBoutons": "rgb(102, 102, 102)",
            "couleurTexteBoutons": "rgb(255, 255, 255)",
            "couleurBoutonsBad": "linear-gradient(160deg, #d12c2c 0%,#7c1b1b 100%)",
            "couleurTexteBoutonsBad": "rgb(255, 255, 255)",
            "couleurBoutonsClair": "linear-gradient(160deg, #ffffff 0%,#dadada 100%)",
            "couleurTexteBoutonsClair": "#3b3b3b",
            "couleurFondSelecteurs": "rgb(77, 77, 77)",
            "couleurTexteSelecteur": "rgb(0, 0, 0)",
            "couleurFondSelecteursSelection": "rgb(94, 194, 94)",
            "couleurTexteSelecteurSelection": "rgb(0, 0, 0)",
            "couleurFondInfosSelecteur": "rgba(255, 255, 255, 0.418)",
            "couleurTexteInfosSelecteur": "rgba(0, 0, 0, 0.822)",
            "couleurPlaceholderSelecteur": "rgba(0, 0, 0, 0.562)",
            "couleurLabelSelecteurOn": "rgba(0, 0, 0, 0.959)",
            "couleurLabelSelecteurOff": "rgba(0, 0, 0, 0.397)"
        }
    }
}